Lectio/__init__.py
Lectio/lectioCode.py
Lectio-0.0.1.dist-info/LICENSE
Lectio-0.0.1.dist-info/METADATA
Lectio-0.0.1.dist-info/WHEEL
Lectio-0.0.1.dist-info/top_level.txt
Lectio-0.0.1.dist-info/RECORD
