Metadata-Version: 2.1
Name: Lectio
Version: 0.0.1
Summary: A Lectio API, used for accessing lectio.dk
Home-page: https://github.com/danielweper/lectio
Author: Daniel Weper Jensen
Author-email: danielweper@gmail.com
License: UNKNOWN
Project-URL: Bug Tracker, https://github.com/danielweper/lectio/issues
Platform: UNKNOWN
Classifier: Programming Language :: Python :: 3
Classifier: License :: OSI Approved :: MIT License
Classifier: Operating System :: OS Independent
Requires-Python: >=3.6
License-File: LICENSE
